{
   "header": "Chart Anatomy",
   "subHeader": "To know how FusionCharts works it is important to understand the various components and concepts of a chart",
   "content": {
      "header": "Below are different sections with interactive annotated images describing various components and concepts of charts",
      "contentGroup": [
         {
            "itemHeader": "Stacked Chart",
            "imgSrc": "stacked-chart-anatomy.png",
            "annotations": [{
                  "annotationNumber": "1",
                  "annotationName": "Caption",
                  "annotationDesc": "The caption (also called the chart title) is the heading of your chart. You can add custom text for the caption, as well as configure its font properties and cosmetics.",
                  "annotationDescLinkPath": null,
                  "leftPosition": "34%",
                  "topPosition": "10.5%",
                  "annotationLinks": [{
                        "linkDesc": "Learn how to add caption ",
                        "linkPath": "/chart-guide/chart-configurations/caption-and-sub-caption#set-the-caption-and-subcaption"
                     },
                     {
                        "linkDesc": "Font properties and cosmetics of caption can also be customized using attributes. Know more about them ",
                        "linkPath": "/chart-guide/chart-configurations/caption-and-sub-caption#customize-font-properties"
                     },
                     {
                        "linkDesc": "You can also customize the alignment of the caption. Learn more about it ",
                        "linkPath": "/chart-guide/chart-configurations/caption-and-sub-caption#configure-caption-alignment"
                     }
                  ]
               },
               {
                  "annotationNumber": "2",
                  "annotationName": "Subcaption",
                  "annotationDesc": "The subcaption (also called the chart subtitle) is the sub-heading of your chart. You can add custom text for subcaption, as well as configure its font properties. Learn more about it ",
                  "annotationDescLinkPath": null,
                  "leftPosition": "57%",
                  "topPosition": "16.5%",
                  "annotationLinks": [{
                        "linkDesc": "Learn how to add subcaption ",
                        "linkPath": "/chart-guide/chart-configurations/caption-and-sub-caption#set-the-caption-and-subcaption"
                     },
                     {
                        "linkDesc": "Font properties and cosmetics of subcaption can also be customized using attributes. Learn more about them ",
                        "linkPath": "/chart-guide/chart-configurations/caption-and-sub-caption#customize-font-properties"
                     }
                  ]
               },
               {
                  "annotationNumber": "3",
                  "annotationName": "Canvas Area",
                  "annotationDesc": "Canvas area refers to the area in which the chart data is plotted, excluding the area where titles, legends, and axis names are rendered.",
                  "annotationDescLinkPath": null,
                  "leftPosition": "82%",
                  "topPosition": "30%",
                  "annotationLinks": [{
                        "linkDesc": "You can customize border for canvas. Learn more about it ",
                        "linkPath": "/chart-guide/chart-configurations/canvas#show-canvas-border"
                     },
                     {
                        "linkDesc": "You can customize background color for canvas, as well as add gradient fill to it. Learn more about it ",
                        "linkPath": "/chart-guide/chart-configurations/canvas#use-gradient-fill"
                     }
                  ]
               },
               {
                  "annotationNumber": "4",
                  "annotationName": "X-Axis",
                  "annotationDesc": "X-Axis refers to line or values on a chart that runs horizontally (left-right). Learn more about it ",
                  "annotationDescLinkPath": "/chart-guide/chart-configurations/titles-and-axis-names",
                  "leftPosition": "80%",
                  "topPosition": "63%",
                  "annotationLinks": []
               },
               {
                  "annotationNumber": "5",
                  "annotationName": "X-Axis Title",
                  "annotationDesc": "X-Axis refers to title of the x-axis. Learn more about it ",
                  "annotationDescLinkPath": "/chart-guide/chart-configurations/titles-and-axis-names#setting-axes-names",
                  "leftPosition": "55%",
                  "topPosition": "72%",
                  "annotationLinks": []
               },
               {
                  "annotationNumber": "6",
                  "annotationName": "X-Axis Labels",
                  "annotationDesc": "X-Axis labels are the names of the data points that are displayed on the x-axis of a chart. Learn more about it ",
                  "annotationDescLinkPath": "/chart-guide/chart-configurations/titles-and-axis-names#setting-axes-names",
                  "leftPosition": "38.5%",
                  "topPosition": "66%",
                  "annotationLinks": []
               },
               {
                  "annotationNumber": "7",
                  "annotationName": "Y-Axis",
                  "annotationDesc": "Y-Axis refers to  line or values on a chart that runs vertically (up-down) through zero. Learn more about it ",
                  "annotationDescLinkPath": "/chart-guide/chart-configurations/titles-and-axis-names#setting-axes-names",
                  "leftPosition": "13%",
                  "topPosition": "68%",
                  "annotationLinks": []
               },
               {
                  "annotationNumber": "8",
                  "annotationName": "Y-Axis Title",
                  "annotationDesc": "Y-Axis refers to the title of the y-axis. Learn more about it ",
                  "annotationDescLinkPath": "/chart-guide/chart-configurations/titles-and-axis-names",
                  "leftPosition": "7%",
                  "topPosition": "40%",
                  "annotationLinks": []
               },
               {
                  "annotationNumber": "9",
                  "annotationName": "Data Plot",
                  "annotationDesc": "Data plot refers to the columns of the column chart, lines in a line chart, pie/doughnut slices in a pie/doughnut chart.",
                  "annotationDescLinkPath": null,
                  "leftPosition": "74%",
                  "topPosition": "51.5%",
                  "annotationLinks": [{
                     "linkDesc": "You can customize the way your data plot looks using colors, gradients and hover effects using available attributes. Learn more about their usage ",
                     "linkPath": "/chart-guide/chart-configurations/data-plot"
                  }]
               },
               {
                  "annotationNumber": "10",
                  "annotationName": "Legend",
                  "annotationDesc": "A legend is a chart element used to display the series name for each dataset, in case of multi-series or combination charts. Legends are used to correlate a data plot to its series name using its color.",
                  "annotationDescLinkPath": null,
                  "leftPosition": "32.5%",
                  "topPosition": "78.5%",
                  "annotationLinks": [{
                        "linkDesc": "You can customize look and feel of legend like increase/decrease legend icon size, define custom legend icons, legend scroll, etc. Learn more about it ",
                        "linkPath": "/chart-guide/chart-configurations/legend#configure-legend-icon-size"
                     },
                     {
                        "linkDesc": "You can customize legend position on the chart either to right or bottom of the chart. Learn more about it ",
                        "linkPath": "/chart-guide/chart-configurations/legend#set-the-legend-position"
                     },
                     {
                        "linkDesc": "You can highlight data plots by hovering over corresponding legend item using plot highlight effects. Learn more about them ",
                        "linkPath": "/chart-guide/chart-configurations/legend#highlight-a-data-series-via-the-legend"
                     }
                  ]
               },
               {
                  "annotationNumber": "11",
                  "annotationName": "Tooltip",
                  "annotationDesc": "A tooltip is displayed when the mouse cursor hovers over a particular data point. It denotes valuable information about the data plot hovered.",
                  "annotationDescLinkPath": "/chart-guide/chart-configurations/titles-and-axis-names#setting-axes-names",
                  "leftPosition": "65.5%",
                  "topPosition": "25.5%",
                  "annotationLinks": [{
                        "linkDesc": "You can customize padding, size and other properties of tooltips. Learn more about them ",
                        "linkPath": "/chart-guide/chart-configurations/tool-tips#customize-tooltips"
                     },
                     {
                        "linkDesc": "You can also customize the text of tooltip and use values plotted on the chart using macros. Learn more about it ",
                        "linkPath": "/chart-guide/chart-configurations/tool-tips#introduction-to-macros"
                     }
                  ]
               },
               {
                  "annotationNumber": "12",
                  "annotationName": "Export Menu",
                  "annotationDesc": "Export menu is hamburger menu that appears on top-right of the chart by hovering on which you can export the chart using available options.",
                  "annotationDescLinkPath": null,
                  "leftPosition": "85.5%",
                  "topPosition": "9%",
                  "annotationLinks": [{
                        "linkDesc": "You can enable or disable chart export using attribute `exportEnabled`. Learn more about its usage ",
                        "linkPath": "/exporting-charts/using-fc-export-server/exporting-charts-as-image-and-pdf"
                     },
                     {
                        "linkDesc": "You can also define export mode like `server`, `client`, or `auto` for chart export. Learn more about them ",
                        "linkPath": "/exporting-charts/using-fc-export-server/modes-of-export/exporting-charts-and-chart-data-using-the-server-side-export-feature"
                     },
                     {
                        "linkDesc": "Look and feel of this menu can also be customized using available attributes. Learn more about them ",
                        "linkPath": "/chart-attributes/area2d"
                     }
                  ]
               },
               {
                  "annotationNumber": "13",
                  "annotationName": "Data Values",
                  "annotationDesc": "Data values are plot values, i.e. values of each data plot (line, column, bar, pie) displayed on the chart. Learn more about it ",
                  "annotationDescLinkPath": "/chart-guide/chart-configurations/data-values",
                  "leftPosition": "27%",
                  "topPosition": "22%",
                  "annotationLinks": []
               }
            ]
         }
      ]
   }
}
